axc/__init__.py
axm/__init__.py
ax_tools-0.6.dist-info/METADATA
ax_tools-0.6.dist-info/WHEEL
ax_tools-0.6.dist-info/top_level.txt
ax_tools-0.6.dist-info/RECORD
