Metadata-Version: 2.1
Name: ax-tools
Version: 0.6
Summary: Tools for Axyl AX System
Home-page: http://github.com/Omega0x013/ax-tools
Author: Alexander Bielby
Author-email: xanderbielby@gmail.com
License: GNU GPLv3
Platform: UNKNOWN
